<?xml version="1.0" encoding="UTF-8"?>
<resource name="spencerhyman" restype="4" id="2807404">
  <chart from="1128859201" to="1129464001">
    <entry name="The Police" reach="136911" counter="1"/>
    <entry name="Whitesnake" reach="49160" counter="1"/>
    <entry name="Dire Straits" reach="117606" counter="1"/>
    <entry name="The Pretenders" reach="49112" counter="1"/>
    <entry name="Shania Twain" reach="51007" counter="1"/>
    <entry name="Evanescence" reach="193354" counter="1"/>
  </chart>
  <chart from="1132488002" to="1133092802"/>
  <chart from="1133092801" to="1133697601">
    <entry name="The Human League" reach="37418" counter="3"/>
    <entry name="Tina Turner" reach="40816" counter="3"/>
    <entry name="Madonna" reach="215412" counter="2"/>
    <entry name="Blondie" reach="106230" counter="2"/>
    <entry name="Simple Minds" reach="41935" counter="2"/>
    <entry name="Cyndi Lauper" reach="59251" counter="2"/>
    <entry name="Bananarama" reach="24600" counter="2"/>
    <entry name="Paula Abdul" reach="15990" counter="2"/>
    <entry name="Pet Shop Boys" reach="72490" counter="1"/>
    <entry name="Cher" reach="38263" counter="1"/>
    <entry name="Kylie Minogue" reach="97549" counter="1"/>
    <entry name="49ers" reach="1184" counter="1"/>
    <entry name="Belinda Carlisle" reach="24576" counter="1"/>
    <entry name="Deana Carter" reach="8231" counter="1"/>
    <entry name="Level 42" reach="13112" counter="1"/>
    <entry name="Sabrina" reach="4757" counter="1"/>
    <entry name="Westworld" reach="687" counter="1"/>
    <entry name="The Go-Go's" reach="15647" counter="1"/>
    <entry name="the Models" reach="489" counter="1"/>
  </chart>
  <chart from="1133697601" to="1134302401">
    <entry name="Cyndi Lauper" reach="59251" counter="2"/>
    <entry name="Starship" reach="14601" counter="2"/>
    <entry name="Blondie" reach="106230" counter="1"/>
    <entry name="Mike &amp; the Mechanics" reach="14103" counter="1"/>
    <entry name="Belinda Carlisle" reach="24576" counter="1"/>
    <entry name="Pat Benatar" reach="34922" counter="1"/>
    <entry name="Sabrina" reach="4757" counter="1"/>
  </chart>
  <chart from="1136721601" to="1137326401"/>
  <chart from="1137326402" to="1137931202">
    <entry name="Ludwig van Beethoven" reach="111754" counter="1"/>
    <entry name="Carly Simon" reach="29528" counter="1"/>
    <entry name="Samuel Barber" reach="14097" counter="1"/>
    <entry name="Simple Minds" reach="41935" counter="1"/>
    <entry name="Starship" reach="14601" counter="1"/>
    <entry name="Faith Hill" reach="38710" counter="1"/>
    <entry name="Belinda Carlisle" reach="24576" counter="1"/>
    <entry name="Level 42" reach="13112" counter="1"/>
    <entry name="Antonio Vivaldi" reach="45887" counter="1"/>
    <entry name="Franz Schubert" reach="24464" counter="1"/>
    <entry name="Henry Purcell" reach="9023" counter="1"/>
    <entry name="Camille Saint-Saëns" reach="17104" counter="1"/>
  </chart>
  <chart from="1138536002" to="1139140802">
    <entry name="Starship" reach="14601" counter="2"/>
    <entry name="Billy Idol" reach="80805" counter="1"/>
    <entry name="Texas" reach="37831" counter="1"/>
    <entry name="Madonna" reach="215412" counter="1"/>
    <entry name="Simply Red" reach="32228" counter="1"/>
    <entry name="The Police" reach="136911" counter="1"/>
    <entry name="Blondie" reach="106230" counter="1"/>
    <entry name="Sheena Easton" reach="9998" counter="1"/>
    <entry name="Kirsty MacColl" reach="9600" counter="1"/>
    <entry name="REO Speedwagon" reach="22810" counter="1"/>
    <entry name="Mike &amp; the Mechanics" reach="14103" counter="1"/>
    <entry name="Shania Twain" reach="51007" counter="1"/>
    <entry name="Annie Lennox" reach="39446" counter="1"/>
    <entry name="Tina Turner" reach="40816" counter="1"/>
    <entry name="Stevie Nicks" reach="16438" counter="1"/>
    <entry name="The Corrs" reach="60962" counter="1"/>
    <entry name="Cyndi Lauper" reach="59251" counter="1"/>
    <entry name="Kylie Minogue" reach="97549" counter="1"/>
    <entry name="Bananarama" reach="24600" counter="1"/>
    <entry name="Frankie Goes to Hollywood" reach="31602" counter="1"/>
    <entry name="ABBA" reach="78243" counter="1"/>
    <entry name="Eddie Money" reach="13504" counter="1"/>
    <entry name="Mr. Mister" reach="15151" counter="1"/>
    <entry name="Belinda Carlisle" reach="24576" counter="1"/>
    <entry name="Deana Carter" reach="8231" counter="1"/>
    <entry name="Pat Benatar" reach="34922" counter="1"/>
    <entry name="Howard Jones" reach="12265" counter="1"/>
    <entry name="Martine McCutcheon" reach="2338" counter="1"/>
    <entry name="Sinitta" reach="1496" counter="1"/>
  </chart>
  <chart from="1142164802" to="1142769602">
    <entry name="James Brown" reach="89801" counter="1"/>
  </chart>
  <chart from="1146398400" to="1147003200"/>
  <chart from="1147608000" to="1148212800"/>
  <chart from="1150027200" to="1150632000"/>
  <chart from="1152446400" to="1153051200"/>
  <chart from="1154865600" to="1155470400">
    <entry name="Van Halen" reach="89716" counter="1"/>
    <entry name="The Velvet Underground" reach="156143" counter="1"/>
    <entry name="Peter Gabriel" reach="89010" counter="1"/>
    <entry name="Status Quo" reach="29070" counter="1"/>
    <entry name="The Pogues" reach="44137" counter="1"/>
    <entry name="The Pretenders" reach="49112" counter="1"/>
    <entry name="Seal" reach="62486" counter="1"/>
    <entry name="Billy Joel" reach="106087" counter="1"/>
    <entry name="ABBA" reach="78243" counter="1"/>
    <entry name="John Mellencamp" reach="31910" counter="1"/>
    <entry name="Richard Thompson" reach="8627" counter="1"/>
    <entry name="Cat Power" reach="123595" counter="1"/>
    <entry name="Uncle Tupelo" reach="20107" counter="1"/>
    <entry name="The Jayhawks" reach="13423" counter="1"/>
  </chart>
  <chart from="1156680000" to="1157284800">
    <entry name="Paulina Rubio" reach="9764" counter="1"/>
  </chart>
  <chart from="1157284800" to="1157889600">
    <entry name="Nina Simone" reach="84712" counter="1"/>
    <entry name="Wolfgang Amadeus Mozart" reach="85198" counter="1"/>
  </chart>
  <chart from="1157889600" to="1158494400"/>
  <chart from="1159704000" to="1160308800">
    <entry name="Dire Straits" reach="117606" counter="2"/>
    <entry name="The White Stripes" reach="304856" counter="1"/>
    <entry name="Bryan Adams" reach="99900" counter="1"/>
    <entry name="Janis Joplin" reach="56621" counter="1"/>
    <entry name="Paul McCartney &amp; Wings" reach="23577" counter="1"/>
    <entry name="Toto" reach="46247" counter="1"/>
    <entry name="The Beach Boys" reach="161945" counter="1"/>
    <entry name="T. Rex" reach="56952" counter="1"/>
    <entry name="The Who" reach="178882" counter="1"/>
    <entry name="Sly &amp; The Family Stone" reach="36576" counter="1"/>
  </chart>
</resource>
